qwiic_pir.py
sparkfun_qwiic_pir-0.0.4.dist-info/LICENSE
sparkfun_qwiic_pir-0.0.4.dist-info/METADATA
sparkfun_qwiic_pir-0.0.4.dist-info/WHEEL
sparkfun_qwiic_pir-0.0.4.dist-info/top_level.txt
sparkfun_qwiic_pir-0.0.4.dist-info/RECORD
