Metadata-Version: 1.1
Name: sparkfun_qwiic_pir
Version: 0.0.4
Summary: SparkFun Electronics qwiic example package
Home-page: http://www.sparkfun.com/qwiic
Author: SparkFun Electronics
Author-email: info@sparkfun.com
License: MIT
Keywords: electronics,maker
Platform: UNKNOWN
Classifier: Development Status :: 3 - Alpha
Classifier: Intended Audience :: Developers
Classifier: Topic :: Software Development :: Build Tools
Classifier: License :: OSI Approved :: MIT License
Classifier: Programming Language :: Python :: 2.7
Classifier: Programming Language :: Python :: 3.5
Classifier: Programming Language :: Python :: 3.6
Classifier: Programming Language :: Python :: 3.7
